AUTHORS
CHANGELOG
MANIFEST.in
README.markdown
pysmell.el
pysmell.vim
setup.py
PySmell.tmbundle/info.plist
PySmell.tmbundle/Commands/Complete.tmCommand
PySmell.tmbundle/Commands/Tags.tmCommand
pysmell/__init__.py
pysmell/codefinder.py
pysmell/emacshelper.py
pysmell/idehelper.py
pysmell/matchers.py
pysmell/tags.py
pysmell/textmate.py
pysmell/tm_dialog.py
pysmell/vimhelper.py
pysmell.egg-info/PKG-INFO
pysmell.egg-info/SOURCES.txt
pysmell.egg-info/dependency_links.txt
pysmell.egg-info/entry_points.txt
pysmell.egg-info/top_level.txt